[
    {
        "filename": "0.png",
        "text": "你有空嗎?"
    },
    {
        "filename": "1.png",
        "text": "什麼!什麼!"
    },
    {
        "filename": "2.png",
        "text": "沒有錯辣!"
    },
    {
        "filename": "3.png",
        "text": "嘖嘖嘖嘖"
    },
    {
        "filename": "4.png",
        "text": "不思進取只想放假"
    },
    {
        "filename": "5.png",
        "text": "賀喔"
    },
    {
        "filename": "6.png",
        "text": "(呈現廢物狀態)"
    },
    {
        "filename": "7.png",
        "text": "(弱小無助)"
    },
    {
        "filename": "8.png",
        "text": "我被棉被綁架了!"
    },
    {
        "filename": "9.png",
        "text": "上班使我快樂!"
    },
    {
        "filename": "10.png",
        "text": "等下要吃什麼"
    },
    {
        "filename": "11.png",
        "text": "你說什麼都是對的"
    },
    {
        "filename": "12.png",
        "text": "喜翻"
    },
    {
        "filename": "14.png",
        "text": "新年快樂明年暴富"
    },
    {
        "filename": "15.png",
        "text": "聖蛋快樂!"
    },
    {
        "filename": "16.png",
        "text": "快逃"
    },
    {
        "filename": "17.png",
        "text": "你是被虐狂嗎"
    },
    {
        "filename": "18.png",
        "text": "我不想幹了"
    },
    {
        "filename": "19.png",
        "text": "我想離職!"
    },
    {
        "filename": "20.png",
        "text": "(拒絕接收任佝訊息)"
    },
    {
        "filename": "21.png",
        "text": "(好想離開這裡)"
    },
    {
        "filename": "22.png",
        "text": "自由了!!!"
    },
    {
        "filename": "23.png",
        "text": "(被現實打醒)"
    },
    {
        "filename": "24.png",
        "text": "你要預約什麼時候"
    },
    {
        "filename": "25.png",
        "text": "這個時間不行喔"
    },
    {
        "filename": "26.png",
        "text": "不好意思都約滿了下次請早"
    },
    {
        "filename": "27.png",
        "text": "總裁今天不待客請回吧"
    },
    {
        "filename": "28.png",
        "text": "找我請先預約"
    },
    {
        "filename": "29.png",
        "text": "下班後不談公事"
    },
    {
        "filename": "30.png",
        "text": "自己想辦法"
    },
    {
        "filename": "31.png",
        "text": "我先忙一下等等回你"
    },
    {
        "filename": "32.png",
        "text": "下班啦!!!!"
    },
    {
        "filename": "33.png",
        "text": "我為什麼會在這裡"
    },
    {
        "filename": "34.png",
        "text": "為錢出賣自己的靈魂"
    },
    {
        "filename": "35.png",
        "text": "YA~上班囉"
    },
    {
        "filename": "36.png",
        "text": "我以為我可以"
    },
    {
        "filename": "37.png",
        "text": "其膏我不行"
    },
    {
        "filename": "38.png",
        "text": "然後就這樣了"
    },
    {
        "filename": "39.png",
        "text": "我不想管了"
    }
]